{
    "default":  {
                    "PricePenaltyFactor":  1,
                    "Wallet":  "134bw4oTorEJUUVFhokDQDfNqTs7rBMNYy",
                    "UserName":  "mrplus",
                    "WorkerName":  "NPlusMinerRocks",
                    "APIKey":  "2c7f2ab04f6dc195db661b7b854e70c5a3bddb90b610f8fc70238b0b4b6a3f78"
                },
    "phiphipoolplus":  {
                           "PricePenaltyFactor":  1,
                           "Wallet":  "134bw4oTorEJUUVFhokDQDfNqTs7rBMNYy",
                           "UserName":  "mrplus",
                           "WorkerName":  "NPlusMinerRocks",
                           "APIKey":  "2c7f2ab04f6dc195db661b7b854e70c5a3bddb90b610f8fc70238b0b4b6a3f78",
                           "Algorithm":  [
                                             "+x21s"
                                         ]
                       }
}
