{
  "americas": ["USA West", "USA East", "Europe", "Russia", "HongKong", "Japan", "Asia"],
  "as":       ["Asia", "HongKong", "Japan", "Russia", "Europe", "USA East", "USA West"],
  "Asia":     ["Asia", "HongKong", "Japan", "Russia", "Europe", "USA East", "USA West"],
  "aspac":    ["Asia", "HongKong", "Japan", "Russia", "Europe", "USA East", "USA West"],
  "eu":       ["Europe", "Russia", "USA West", "USA East", "HongKong", "Asia", "Japan"],
  "eu-west":  ["Europe", "Russia", "USA West", "USA East", "HongKong", "Asia", "Japan"],
  "Europe":   ["Europe", "Russia", "USA West", "USA East", "HongKong", "Asia", "Japan"],
  "hk":       ["HongKong", "Asia", "Japan", "Russia", "Europe", "USA East", "USA West"],
  "HongKong": ["HongKong", "Asia", "Japan", "Russia", "Europe", "USA East", "USA West"],
  "Japan":    ["Japan", "HongKong", "Asia", "Russia", "Europe", "USA East", "USA West"],
  "jp":       ["Japan", "HongKong", "Asia", "Russia", "Europe", "USA East", "USA West"],
  "na":       ["USA West", "USA East", "Europe", "Russia", "HongKong", "Asia", "Japan"],
  "Russia":   ["Russia", "Europe", "HongKong", "Asia", "Japan", "USA East", "USA West"],
  "ru":       ["Russia", "Europe", "HongKong", "Asia", "Japan", "USA West", "USA East"],
  "sea":      ["Asia", "HongKong", "Japan", "Russia", "Europe", "USA East", "USA West"],
  "us":       ["USA West", "USA East", "Europe", "Russia", "HongKong", "Japan", "Asia"],
  "us-east":  ["USA East", "USA West", "Japan", "HongKong", "Asia", "Russia", "Europe"],
  "naw":      ["USA West", "USA East", "Europe", "Russia", "HongKong", "Asia", "Japan"],
  "usa":      ["USA West", "USA East", "Europe", "Russia", "HongKong", "Japan", "Asia"],
  "use":      ["USA East", "USA West", "Japan", "HongKong", "Asia", "Russia", "Europe"],
  "usw":      ["USA West", "USA East", "Europe", "Russia", "HongKong", "Asia", "Japan"],
  "USA East": ["USA East", "USA West", "Japan", "HongKong", "Asia", "Russia", "Europe"],
  "USA West": ["USA West", "USA East", "Europe", "Russia", "HongKong", "Asia", "Japan"]
}
